szte_qp_grader/__init__.py
szte_qp_grader/qp_grader.py
szte_qp_grader-0.0.1.dist-info/METADATA
szte_qp_grader-0.0.1.dist-info/WHEEL
szte_qp_grader-0.0.1.dist-info/top_level.txt
szte_qp_grader-0.0.1.dist-info/RECORD
