Metadata-Version: 2.1
Name: szte-qp-grader
Version: 0.0.1
Summary: Grading Qiskit exercises
Home-page: UNKNOWN
Author: András Czégel
License: UNKNOWN
Platform: UNKNOWN
Requires-Dist: Qiskit
Requires-Dist: numpy
